README
setup.py
django_slumber.egg-info/PKG-INFO
django_slumber.egg-info/SOURCES.txt
django_slumber.egg-info/dependency_links.txt
django_slumber.egg-info/pbr.json
django_slumber.egg-info/requires.txt
django_slumber.egg-info/top_level.txt
slumber/__init__.py
slumber/_caches.py
slumber/configuration.py
slumber/fields.py
slumber/forms.py
slumber/scheme.py
slumber/test.py
slumber/urls.py
slumber/connector/__init__.py
slumber/connector/api.py
slumber/connector/authentication.py
slumber/connector/configuration.py
slumber/connector/dictobject.py
slumber/connector/json.py
slumber/connector/middleware.py
slumber/connector/proxies.py
slumber/connector/ua.py
slumber/operations/__init__.py
slumber/operations/authenticate.py
slumber/operations/authorization.py
slumber/operations/create.py
slumber/operations/delete.py
slumber/operations/instancedata.py
slumber/operations/instancelist.py
slumber/operations/profile.py
slumber/operations/search.py
slumber/operations/update.py
slumber/server/__init__.py
slumber/server/accept_handler.py
slumber/server/application.py
slumber/server/html.py
slumber/server/http.py
slumber/server/json.py
slumber/server/meta.py
slumber/server/model.py
slumber/server/views.py
slumber/server/xml.py
slumber_ex_shop/__init__.py
slumber_ex_shop/models.py
slumber_examples/__init__.py
slumber_examples/admin.py
slumber_examples/models.py
slumber_examples/operations.py
slumber_examples/slumber_client.py
slumber_examples/slumber_server.py
slumber_examples/views.py
slumber_examples/nested1/__init__.py
slumber_examples/nested1/nested2/__init__.py
slumber_examples/no_models/__init__.py
slumber_examples/no_models/models.py
slumber_examples/tests/__init__.py
slumber_examples/tests/accept_handler.py
slumber_examples/tests/application_configuration.py
slumber_examples/tests/authentication.py
slumber_examples/tests/client.py
slumber_examples/tests/configurations.py
slumber_examples/tests/forms.py
slumber_examples/tests/hal.py
slumber_examples/tests/html.py
slumber_examples/tests/json.py
slumber_examples/tests/middleware.py
slumber_examples/tests/mock_client.py
slumber_examples/tests/models.py
slumber_examples/tests/operations.py
slumber_examples/tests/proxies.py
